{"weight_typical": 1513.026, "duration_typical": 1471.501, "weight_name": "auto", "weight": 1570.459, "duration": 1528.934, "distance": 22331.156, "legs": [{"via_waypoints": [], "admins": [{"iso_3166_1_alpha3": "USA", "iso_3166_1": "US"}], "weight_typical": 1513.026, "duration_typical": 1471.501, "weight": 1570.459, "duration": 1528.934, "steps": [], "distance": 22331.156, "summary": "I 5 North, I 84 East"}], "geometry": "irktGhwglV?|A~H?@y]bT?@yw@lGA}EuW?{RsTwr@ug@ye@wHmbAa_B}_D_BceAu`BtEmd@q_@yh@qCef@zAoZoh@uOz@gPS}}@uRw\\u}A_EstAgUs_@nAuXbDmQkKKexAc`FwNI"}