{"weight_typical": 2216.713, "duration_typical": 1540.231, "weight_name": "auto", "weight": 2226.888, "duration": 1550.252, "distance": 22745.275, "legs": [{"via_waypoints": [], "admins": [{"iso_3166_1_alpha3": "USA", "iso_3166_1": "US"}], "weight_typical": 2216.713, "duration_typical": 1540.231, "weight": 2226.888, "duration": 1550.252, "steps": [], "distance": 22745.275, "summary": "Clackamas Highway, South Forsythe Road"}], "geometry": "ctysGl{wiVm@bBmO`MfIpX}~AfqBioAnrBa`@htBaSlj@`V|wAj\\bk@lE~j@iDl`@aRd]kd@tKgQvo@n@lb@rK|c@gG|]xNja@uBpa@jNf@zI{MpKbHbLzf@uCnk@zLxl@iFFu@lp@|]lp@?pzDhHhBnO`v@nV?hAwD"}