{"weight_typical": 2255.481, "duration_typical": 1302.793, "weight_name": "auto", "weight": 2236.733, "duration": 1283.81, "distance": 16626.086, "legs": [{"via_waypoints": [], "admins": [{"iso_3166_1_alpha3": "USA", "iso_3166_1": "US"}], "weight_typical": 2255.481, "duration_typical": 1302.793, "weight": 2236.733, "duration": 1283.81, "steps": [], "distance": 16626.086, "summary": "OR 217, Southwest Jenkins Road"}], "geometry": "kwltGta`lVk@J}@_EzDj@N~Q`EpO|b@j]nJfa@lQv{@ng@~sAVvEg}@pyBiJzJoV`H{i@`@wa@jHot@Fuj@v_@kYfH_mAeIgP_HkK`r@jBlTmHzZrNpHwl@bpDxMxDJ^bFf@"}