{"weight_typical": 1987.829, "duration_typical": 1654.155, "weight_name": "auto", "weight": 1987.829, "duration": 1654.155, "distance": 18140.127, "legs": [{"via_waypoints": [], "admins": [{"iso_3166_1_alpha3": "USA", "iso_3166_1": "US"}], "weight_typical": 1987.829, "duration_typical": 1654.155, "weight": 1987.829, "duration": 1654.155, "steps": [], "distance": 18140.127, "summary": "OR 10, OR 217"}], "geometry": "yjrtGze|lVAtAoCMsByMtTsr@yP_~@_V}wDfCafCbl@{Nrl@s`@`aCoIxZ}Il~@quBhyA{gBhg@}PveBdKjQpJXvGqFUfAbI?zD"}