{"weight_typical": 1300.914, "duration_typical": 1182.182, "weight_name": "auto", "weight": 1242.554, "duration": 1123.822, "distance": 15735.164, "legs": [{"via_waypoints": [], "admins": [{"iso_3166_1_alpha3": "USA", "iso_3166_1": "US"}], "weight_typical": 1300.914, "duration_typical": 1182.182, "weight": 1242.554, "duration": 1123.822, "steps": [], "distance": 15735.164, "summary": "Northeast Killingsworth Street, I 205 South"}], "geometry": "knauGpamkVC_XaO?P_uHrFq_@bh@zHxp@oh@znBh]`tHnGqObbAwJj]yBmC"}