{"weight_typical": 1800.12, "duration_typical": 1754.054, "weight_name": "auto", "weight": 1671.12, "duration": 1626.173, "distance": 20361.273, "legs": [{"via_waypoints": [], "admins": [{"iso_3166_1_alpha3": "USA", "iso_3166_1": "US"}], "weight_typical": 1800.12, "duration_typical": 1754.054, "weight": 1671.12, "duration": 1626.173, "steps": [], "distance": 20361.273, "summary": "OR 99E, I 84 East"}], "geometry": "wlbtG`llkV[w@{_BrgAsbB`Q_j@le@mi@bH{xBkZqfBvZku@pmAev@v\\e{CbB{ZggAiE_vA}U_e@bNoeArXyl@bAmZlDuL@qImJ?CyFqBkE"}