{"weight_typical": 1879.835, "duration_typical": 1592.458, "weight_name": "auto", "weight": 1879.835, "duration": 1591.867, "distance": 27185.629, "legs": [{"via_waypoints": [], "admins": [{"iso_3166_1_alpha3": "USA", "iso_3166_1": "US"}], "weight_typical": 1879.835, "duration_typical": 1592.458, "weight": 1879.835, "duration": 1591.867, "steps": [], "distance": 27185.629, "summary": "Northeast Lombard Street, I 205 South"}], "geometry": "wecuGvplkVzAAH}FuKzBzUcbC~X_|@dGsxC`h@zGpo@kh@`pBf]tnJl@~|A`o@|yC{l@tkAfs@voAsQdpBnj@zNfK|FvOmw@pq@}A{A_ExCoBjC"}