{"weight_typical": 3500.461, "duration_typical": 3430.514, "weight_name": "auto", "weight": 3059.363, "duration": 2989.61, "distance": 55035.141, "legs": [{"via_waypoints": [], "admins": [{"iso_3166_1_alpha3": "USA", "iso_3166_1": "US"}], "weight_typical": 3500.461, "duration_typical": 3430.514, "weight": 3059.363, "duration": 2989.61, "steps": [], "distance": 55035.141, "summary": "Banfield Freeway, US 26"}], "geometry": "c|ttGlckjVD`Vwt@lC[t_CkhFnI@yO_B|dEs_@xhG|Jnw@t|@bSxXnl@{WrwBtr@f~Bqj@ndCdV~c@~DntAzYvnArSbX`kA`EvQnXdFzy@k\\tn@iFdCwRdIiGtp@tz@bfBcRfmAvV`sD_GrkBkcHrqWs{@``DeLzOthBgCdWlw@|n@v`@zf@qVdLrv@UkC"}