{"weight_typical": 2150.524, "duration_typical": 1260.987, "weight_name": "auto", "weight": 2214.941, "duration": 1320.62, "distance": 20279.459, "legs": [{"via_waypoints": [], "admins": [{"iso_3166_1_alpha3": "USA", "iso_3166_1": "US"}], "weight_typical": 2150.524, "duration_typical": 1260.987, "weight": 2214.941, "duration": 1320.62, "steps": [], "distance": 20279.459, "summary": "East Burnside Street, I 84 East"}], "geometry": "sdztGn{kkVI}bB_c@MgEmK_d@_nApXg|A{Dal@}Wy]au@cMyLo[|AusAh[{lEOalClRgqEkOeoBbLuwAuYirAmBqbAb@AzG_@]rR"}