{"weight_typical": 1957.146, "duration_typical": 1336.351, "weight_name": "auto", "weight": 1978.92, "duration": 1358.126, "distance": 19028.17, "legs": [{"via_waypoints": [], "admins": [{"iso_3166_1_alpha3": "USA", "iso_3166_1": "US"}], "weight_typical": 1957.146, "duration_typical": 1336.351, "weight": 1978.92, "duration": 1358.126, "steps": [], "distance": 19028.17, "summary": "Southeast 122nd Avenue, Clackamas Highway"}], "geometry": "aphtGno_kV}EhArAyi@|Ym_Aj{A}BX{cApFsMjMxAnFazBh^gXln@wJ`KsJlBw`@sGeKeFeUKmGrGoU}BaSuG{Oo@mb@vIed@nFqJp^gFxDmDvHyShHkHhDm`@mE_k@gIkVcRwSwM}g@DeKgHs_@xSsm@j^cqBvo@_jA{GcM"}