{"weight_typical": 503.264, "duration_typical": 459.193, "weight_name": "auto", "weight": 527.107, "duration": 483.036, "distance": 7192.114, "legs": [{"via_waypoints": [], "admins": [{"iso_3166_1_alpha3": "USA", "iso_3166_1": "US"}], "weight_typical": 503.264, "duration_typical": 459.193, "weight": 527.107, "duration": 483.036, "steps": [], "distance": 7192.114, "summary": "OR 99W, I 5 North"}], "geometry": "soitG`zelVsM\\_BuDkKiY}BcPLeQgJkSoFqYuIsN{V_OmGgJoCeOJq`@sB}Lc{@mjBkPqa@cQyUc@sFrAsKdCeA|E}HmCuNd@gAlAn@"}