{"weight_typical": 1893.726, "duration_typical": 1513.473, "weight_name": "auto", "weight": 1893.726, "duration": 1513.626, "distance": 23814.266, "legs": [{"via_waypoints": [], "admins": [{"iso_3166_1_alpha3": "USA", "iso_3166_1": "US"}], "weight_typical": 1893.726, "duration_typical": 1513.473, "weight": 1893.726, "duration": 1513.626, "steps": [], "distance": 23814.266, "summary": "Banfield Freeway, US 26"}], "geometry": "{tytGhcekV?c@`F?c@tSsV~i@r@tt@qUMAxH{FrFu@hd@{W`k@{MddAfVle@~DntAzYvnAbClSnOtC|s@bMbVaGvQnXjH|OeA|h@k\\tn@iFdCwRdIgGzq@|w@fqAfAr]uQhbApDvoAzOpsAf@fbAcPnyAwfAx~DgQre@wTiIsJjWkDsC[`A"}