{"weight_typical": 2007.612, "duration_typical": 1619.055, "weight_name": "auto", "weight": 2007.612, "duration": 1618.896, "distance": 22958.395, "legs": [{"via_waypoints": [], "admins": [{"iso_3166_1_alpha3": "USA", "iso_3166_1": "US"}], "incidents": [{"id": "9297715225737498", "type": "disabled_vehicle", "creation_time": "2023-12-06T01:30:15Z", "start_time": "2023-12-05T23:58:19Z", "end_time": "2023-12-06T01:44:25Z", "iso_3166_1_alpha2": "US", "iso_3166_1_alpha3": "USA", "description": "I-84 W/B: stalled vehicle at Exit 1 33rd Ave", "long_description": "One lane blocked due to stalled vehicle on I-84 Westbound at Exit 1 33rd Ave.", "impact": "major", "sub_type": "LANE_RESTRICTION", "alertc_codes": [211, 646], "traffic_codes": {"incident_primary_code": 211}, "lanes_blocked": [], "length": 16, "south": 45.530384, "west": -122.637603, "north": 45.530395, "east": -122.637405, "congestion": {"value": 101}, "geometry_index_start": 300, "geometry_index_end": 301, "affected_road_names": ["Banfield Freeway/T. H. Banfield Expressway"], "affected_road_names_unknown": ["I 84 West/US 30"], "affected_road_names_en": ["Banfield Freeway/T. H. Banfield Expressway"]}], "weight_typical": 2007.612, "duration_typical": 1619.055, "weight": 2007.612, "duration": 1618.896, "steps": [], "distance": 22958.395, "summary": "Banfield Freeway, US 26"}], "geometry": "awytGb_`kV@uAr@@AhGjGJ?ze@cw@DoMaCcHdIU|r@uVrpAjr@rvBaAxYqXvl@mN~eAfVle@~DntAzYvnAbClSnOtC|s@bMbVaGvQnXjH|OeA|h@k\\tn@iFdCwRdIgGzq@lw@jnAvAn`@oQl~@xCz`@m@|UnKnMrPgHhPj\\vVuFfNhQnZhKPmjAeFt@"}