{"weight_typical": 1893.993, "duration_typical": 1600.527, "weight_name": "auto", "weight": 2118.116, "duration": 1783.177, "distance": 25105.496, "legs": [{"via_waypoints": [], "admins": [{"iso_3166_1_alpha3": "USA", "iso_3166_1": "US"}], "incidents": [{"id": "12806385934877441", "type": "disabled_vehicle", "creation_time": "2024-10-19T01:47:46Z", "start_time": "2024-10-19T01:10:37Z", "end_time": "2024-10-19T02:10:55Z", "iso_3166_1_alpha2": "US", "iso_3166_1_alpha3": "USA", "description": "US-26 W/B: stalled vehicle after Jefferson St", "long_description": "Right lane blocked due to stalled vehicle on US-26 Westbound after Jefferson St.", "impact": "minor", "sub_type": "LANE_RESTRICTION", "alertc_codes": [211, 520], "traffic_codes": {"incident_primary_code": 211}, "lanes_blocked": [], "length": 18, "south": 45.506881, "west": -122.712402, "north": 45.506916, "east": -122.712181, "congestion": {"value": 101}, "geometry_index_start": 344, "geometry_index_end": 345, "affected_road_names": ["US 26/Sunset Highway"], "affected_road_names_en": ["US 26/Sunset Highway"]}], "weight_typical": 1893.993, "duration_typical": 1600.527, "weight": 2118.116, "duration": 1783.177, "steps": [], "distance": 25105.496, "summary": "I 405 South, US 26"}], "geometry": "_gduGrk|kV_PIKmnClpDqExb@eJvo@|x@btAgB|T~HrPtP_Bty@xu@jiAfAr]uQhbAnWbsEuNtfB_iA`fEgQre@vl@|MvhArt@qWp|Ao\\``AgItB"}