{"weight_typical": 2389.564, "duration_typical": 2332.817, "weight_name": "auto", "weight": 2276.755, "duration": 2220.701, "distance": 36346.262, "legs": [{"via_waypoints": [], "admins": [{"iso_3166_1_alpha3": "USA", "iso_3166_1": "US"}], "weight_typical": 2389.564, "duration_typical": 2332.817, "weight": 2276.755, "duration": 2220.701, "steps": [], "distance": 36346.262, "summary": "Banfield Freeway, US 30"}], "geometry": "wyptGnnekVoDABeg@qUKbH_xAc`HxAsl@Q{XxeCjr@rxBaj@pnCfVle@~DntAzYvnAwDvNgyAhl@cO``@dp@~x@{HrbAgk@~e@wuAf|EamEt}FkbCzqBwyAfaCiUyQrAdC|NiT"}