{"weight_typical": 1351.305, "duration_typical": 1226.428, "weight_name": "auto", "weight": 1308.779, "duration": 1183.902, "distance": 14343.57, "legs": [{"via_waypoints": [], "admins": [{"iso_3166_1_alpha3": "USA", "iso_3166_1": "US"}], "weight_typical": 1351.305, "duration_typical": 1226.428, "weight": 1308.779, "duration": 1183.902, "steps": [], "distance": 14343.57, "summary": "I 5 North, Southeast Powell Boulevard"}], "geometry": "ckotGfl}kVvBs@PUdB@nGc{@{BgVwOgTuJiPtBcp@qGmPa}AbIgZeYyMcG}g@eDqHq@cDtEn@rCzNaBf@~DeJa@eFa{AfEyp@xVk{BsCqpAVygEpNBF\\"}