{"weight_typical": 752.687, "duration_typical": 700.621, "weight_name": "auto", "weight": 786.929, "duration": 734.864, "distance": 10066.284, "legs": [{"via_waypoints": [], "admins": [{"iso_3166_1_alpha3": "USA", "iso_3166_1": "US"}], "weight_typical": 752.687, "duration_typical": 700.621, "weight": 786.929, "duration": 734.864, "steps": [], "distance": 10066.284, "summary": "I 5 South, Southwest Terwilliger Boulevard"}], "geometry": "kwutGjfqkVtB?cKtaAxEfoBwCzEm@eC`CsAbZsAn_@vBf_@`]bz@qA~`@cGfHpLkArVqAxT{@lCg@gIpMl@lM}PtLb@rFhGxi@i@dIqE~G{Ob@cYbEyCr@_E|D\\"}