{"weight_typical": 1041.808, "duration_typical": 576.372, "weight_name": "auto", "weight": 1052.204, "duration": 587.196, "distance": 6015.554, "legs": [{"via_waypoints": [], "admins": [{"iso_3166_1_alpha3": "USA", "iso_3166_1": "US"}], "weight_typical": 1041.808, "duration_typical": 576.372, "weight": 1052.204, "duration": 587.196, "steps": [], "distance": 6015.554, "summary": "Northeast 33rd Drive, Northeast 42nd Avenue"}], "geometry": "mlhuG`aokVFlE|i@uUfr@tG`d@F|DpEoBkCx@qGzBcInHW?bIcEfArKm_AhDmG|GgBnnAE?X"}