{"weight_typical": 2051.863, "duration_typical": 1690.765, "weight_name": "auto", "weight": 2076.712, "duration": 1711.092, "distance": 26939.621, "legs": [{"via_waypoints": [], "admins": [{"iso_3166_1_alpha3": "USA", "iso_3166_1": "US"}], "incidents": [{"id": "169476559711317", "type": "construction", "creation_time": "2023-09-15T08:13:17Z", "start_time": "2023-09-12T00:00:00Z", "end_time": "2023-09-26T00:00:00Z", "iso_3166_1_alpha2": "US", "iso_3166_1_alpha3": "USA", "description": "Lane closures. No to Minimum Delay", "impact": "critical", "alertc_codes": [16], "traffic_codes": {}, "lanes_blocked": [], "length": 2069, "south": 45.542312, "west": -122.509826, "north": 45.542739, "east": -122.483345, "geometry_index_start": 382, "geometry_index_end": 397, "affected_road_names": ["Columbia River Highway"], "affected_road_names_unknown": ["I 84 West/US 30"], "affected_road_names_en": ["Columbia River Highway"]}], "weight_typical": 2051.863, "duration_typical": 1690.765, "weight": 2076.712, "duration": 1711.092, "steps": [], "distance": 26939.621, "summary": "Northeast Hogan Drive, I 84 West"}], "geometry": "}wutGdabjVzOpDd@dJu@pOcXrZwz@`D{YcMkwAtAoMja@eu@M`CjWgKfdAjM~cAt@tp@cRheE@frC}^n`GGj^dKbXl{@fRlXdf@j@|f@{WbsAvq@trBm@r]cNtYeUhZGtVxk@lAhjBgBCtQgA?"}