{"geometry": "{`ntGbfdkVzVH^al@fLgAElDuDfAqXcEgj@m`@aPcF{sB~ByuA}FgNqGKvOlo@sA", "distance": 8096.4, "duration": 853.721, "weight": 770.811, "weight_name": "auto", "duration_typical": 625.757, "weight_typical": 635.944, "legs": [{"steps": [], "summary": "Southeast Johnson Creek Boulevard, I 205 North", "distance": 8096.4, "duration": 853.721, "weight": 770.811, "duration_typical": 625.757, "weight_typical": 635.944, "admins": [{"iso_3166_1": "US", "iso_3166_1_alpha3": "USA"}], "via_waypoints": []}]}