{"weight_typical": 1218.234, "duration_typical": 588.244, "weight_name": "auto", "weight": 1218.234, "duration": 587.807, "distance": 7916.25, "legs": [{"via_waypoints": [], "admins": [{"iso_3166_1_alpha3": "USA", "iso_3166_1": "US"}], "weight_typical": 1218.234, "duration_typical": 588.244, "weight": 1218.234, "duration": 587.807, "steps": [], "distance": 7916.25, "summary": "Northwest Saint Helens Road, US 30"}], "geometry": "yb~tG~t_lVi@mCvK^`LoLzCgQaAsVaH_[iD_h@x@gBxLq@hFqDfKuf@tBcQ}A_Kag@mp@_MuL}EP{KvIcG~AguBKmMaDcQC"}