{"weight_typical": 1326.754, "duration_typical": 1285.293, "weight_name": "auto", "weight": 1310.924, "duration": 1269.462, "distance": 19236.732, "legs": [{"via_waypoints": [], "admins": [{"iso_3166_1_alpha3": "USA", "iso_3166_1": "US"}], "weight_typical": 1326.754, "duration_typical": 1285.293, "weight": 1310.924, "duration": 1269.462, "steps": [], "distance": 19236.732, "summary": "Southeast 60th Avenue, I 84 East"}], "geometry": "eivtG|zikVnEH@dEsSGGol@{uAlA?r@qy@WgEiKs^kz@kDsRv@sSxVsgA?yV{DgTaKmR{KkJau@cMoH_KiCoO|AusAdM_rAbM{yBOalCzPkzDzBcc@s_@lBhIst@I{m@hDJ"}