{"weight_typical": 857.547, "duration_typical": 852.028, "weight_name": "auto", "weight": 1092.139, "duration": 1086.62, "distance": 7289.479, "legs": [{"via_waypoints": [], "admins": [{"iso_3166_1_alpha3": "USA", "iso_3166_1": "US"}], "weight_typical": 857.547, "duration_typical": 852.028, "weight": 1092.139, "duration": 1086.62, "steps": [], "distance": 7289.479, "summary": "North Greeley Avenue, North Willamette Boulevard"}], "geometry": "ig~tGnvukVAwBvO[H`x@aUh@gIb^am@rx@wt@lXwo@GIjZgS|PwIh_@oL@iQbz@jFlD"}