{"weight_typical": 1490.777, "duration_typical": 1096.721, "weight_name": "auto", "weight": 1490.777, "duration": 1097.525, "distance": 12913.81, "legs": [{"via_waypoints": [], "admins": [{"iso_3166_1_alpha3": "USA", "iso_3166_1": "US"}], "weight_typical": 1490.777, "duration_typical": 1096.721, "weight": 1490.777, "duration": 1097.525, "steps": [], "distance": 12913.81, "summary": "I 84 East, I 205 South"}], "geometry": "mjztGznmkVgB_UaK{@yh@j@lFm`@~Uye@rCySoC{Yyh@cpAeDuPb@wS|Tc~@bBuYnAmRnFiGr{Ba@tPJtNv@v@goB`yA?Tcp@eE?"}