{"weight_typical": 2662.563, "duration_typical": 2638.989, "weight_name": "auto", "weight": 2468.043, "duration": 2444.191, "distance": 47793.34, "legs": [{"via_waypoints": [], "admins": [{"iso_3166_1_alpha3": "USA", "iso_3166_1": "US"}], "weight_typical": 2662.563, "duration_typical": 2638.989, "weight": 2468.043, "duration": 2444.191, "sirns": {}, "steps": [], "distance": 47793.34, "summary": "I 205 North, I 205 South"}], "geometry": "s_ysGtpjlV?qBjnA_FxZk]guD{y@_U_X_ZydB|B_rCdp@}wFxxA{fBxOgx@iWmhC}bAmeBw]u_B{hAqxAg`Dq`AqrAfPmlAqt@wxC|l@q}Akn@ykJKmrBs^in@dg@w[yGeIiXoCj[bh@zHto@oh@|kB|\\"}