{"geometry": "kxvtGtrcjVDlJsO|Cio@eMquAzAoMja@mu@a@hClWeK~eAdOppBiRfiEV|iCw[rtEsB~nBnHvSlsAhSnnDlE}DphBvBrhIxPjB", "distance": 26353.098, "duration": 1981.992, "weight": 1957.301, "weight_name": "auto", "duration_typical": 2075.084, "weight_typical": 2081.369, "legs": [{"steps": [], "summary": "I 84 West, Southeast Division Street", "distance": 26353.098, "duration": 1981.992, "weight": 1957.301, "duration_typical": 2075.084, "weight_typical": 2081.369, "admins": [{"iso_3166_1": "US", "iso_3166_1_alpha3": "USA"}], "via_waypoints": [], "notifications": [{"geometry_index_start": 395, "geometry_index_end": 403, "type": "alert", "subtype": "tunnel", "refresh_type": "static", "details": {"message": "The road leads through a tunnel."}}]}]}