{"weight_typical": 719.518, "duration_typical": 598.135, "weight_name": "auto", "weight": 719.518, "duration": 598.135, "distance": 8738.742, "legs": [{"via_waypoints": [], "admins": [{"iso_3166_1_alpha3": "USA", "iso_3166_1": "US"}], "weight_typical": 719.518, "duration_typical": 598.135, "weight": 719.518, "duration": 598.135, "steps": [], "distance": 8738.742, "summary": "I 84 East, Northeast 238th Drive"}], "geometry": "sm|tGj`pjVo@jEcAdBeb@Fw@aNn@gt@lGilAb@a_@aBsb@uJ{n@s@qOhAwQxGkb@dBwMVwTfl@V`D}EXkOhCmG~DmAvJl@c@sJkK}UIg{@hI?]mP"}