{"weight_typical": 1707.14, "duration_typical": 1075.013, "weight_name": "auto", "weight": 1707.14, "duration": 1075.013, "distance": 16010.112, "legs": [{"via_waypoints": [], "admins": [{"iso_3166_1_alpha3": "USA", "iso_3166_1": "US"}], "weight_typical": 1707.14, "duration_typical": 1075.013, "weight": 1707.14, "duration": 1075.013, "steps": [], "distance": 16010.112, "summary": "I 84 West, Northeast Sandy Boulevard"}], "geometry": "m~|tGd{ajVxBDZvIeCxF}H@zHzjAkUE`CjWgKfdAjM~cAt@tp@cRheE@frCaMrzBcL~hAwCzz@Dbm@{CbSqZlc@oM~GcPeGyFuSnDkzAaFAZ}D"}