{"weight_typical": 911.828, "duration_typical": 850.047, "weight_name": "auto", "weight": 1096.642, "duration": 1034.862, "distance": 8943.533, "legs": [{"via_waypoints": [], "admins": [{"iso_3166_1_alpha3": "USA", "iso_3166_1": "US"}], "weight_typical": 911.828, "duration_typical": 850.047, "weight": 1096.642, "duration": 1034.862, "steps": [], "distance": 8943.533, "summary": "Southwest Murray Boulevard, Southwest Tualatin Valley Highway"}], "geometry": "m_ytG~xrlVdZ~MbR|Sxv@~^nLm@dXmK~TUlEd@ZlAaChc@wGxe@Lzj@uJhqB{BvOFvP}OdvCqHUA~AeBCm@fC"}